{"chart":{"container":"#skills-tree","rootOrientation":"WEST","hideRootNode":true,"connectors":{"type":"bCurve"}},"nodeStructure":{"text":{"name":"Language"},"children":[{"innerHTML":"<div onclick='obtainSkill(\"3343f6aa-ee5c-424c-bcb5-c7447bc5bbb7\", 1)'>Collections</div>","children":[{"innerHTML":"<div onclick='obtainSkill(\"35b38211-3b0f-46d1-af43-c24e4b1fad55\", 1)'>Stream API</div>","children":[],"HTMLid":"35b38211-3b0f-46d1-af43-c24e4b1fad55"}],"HTMLid":"3343f6aa-ee5c-424c-bcb5-c7447bc5bbb7"}]}}